helpit/__init__.py
helpit/core.py
helpit/docs.py
helpit/embeddings.py
helpit/object_info.py
helpit-1.0.0.dist-info/METADATA
helpit-1.0.0.dist-info/WHEEL
helpit-1.0.0.dist-info/top_level.txt
helpit-1.0.0.dist-info/RECORD
