Metadata-Version: 2.4
Name: helpit
Version: 1.0.0
Summary: Ask OpenAI-compatible models about a Python object with runtime metadata and optional help() snippets.
Requires-Python: >=3.9
Requires-Dist: openai>=2.15.0
Provides-Extra: embeddings
Requires-Dist: transformers>=4.46.0; extra == "embeddings"
Requires-Dist: torch>=2.4.0; extra == "embeddings"
Requires-Dist: sentencepiece>=0.1.99; extra == "embeddings"
Provides-Extra: dataframe
Requires-Dist: pandas>=2.2.0; extra == "dataframe"
Provides-Extra: jupyter
Requires-Dist: ipywidgets>=8.1.8; extra == "jupyter"
